code_dataset/__init__.py
code_dataset/cli.py
code_dataset-0.1.1.dist-info/METADATA
code_dataset-0.1.1.dist-info/WHEEL
code_dataset-0.1.1.dist-info/entry_points.txt
code_dataset-0.1.1.dist-info/top_level.txt
code_dataset-0.1.1.dist-info/RECORD
